counter.v
module counter(
    input clk,
    input rst,
    output reg [3:0] count
);

always @(posedge clk or posedge rst)
begin
    if(rst)
        count <= 4'b0000;
    else
        count <= count + 1;
end

endmodule

tb_counter.v
`timescale 1ns/1ps

module tb_counter;

reg clk;
reg rst;
wire [3:0] count;

counter uut(
    .clk(clk),
    .rst(rst),
    .count(count)
);

always #5 clk = ~clk;

initial begin
    clk = 0;
    rst = 1;

    #10 rst = 0;

    #100;

    $finish;
end

initial begin
    $dumpfile("counter.vcd");
    $dumpvars(0,tb_counter);
end

endmodule

counter.vcd
$date
   Wed Jun  3 08:25:21 2026
$end
$version
   ASIC Counter Python Simulator v1.0
$end
$timescale
   1ps
$end
$scope module tb_counter $end
$var reg 1 ! clk $end
$var reg 1 " rst $end
$var wire 4 # count [3:0] $end
$scope module uut $end
$var wire 1 ! clk $end
$var wire 1 " rst $end
$var reg 4 $ count [3:0] $end
$upscope $end
$upscope $end
$enddefinitions $end
#0
$dumpvars
0!
1"
b0000 #
b0000 $
$end
#5000
1!
#10000
0!
0"
#15000
1!
b0001 #
b0001 $
#20000
0!
#25000
1!
b0010 #
b0010 $
#30000
0!
#35000
1!
b0011 #
b0011 $
#40000
0!
#45000
1!
b0100 #
b0100 $
#50000
0!
#55000
1!
b0101 #
b0101 $
#60000
0!
#65000
1!
b0110 #
b0110 $
#70000
0!
#75000
1!
b0111 #
b0111 $
#80000
0!
#85000
1!
b1000 #
b1000 $
#90000
0!
#95000
1!
b1001 #
b1001 $
#100000
0!
#105000
1!
b1010 #
b1010 $
